src/interpolatingvalue.py
src/pathreader.py
src/circle.py
src/rotation2D.py
src/interpolable.py
src/peekorator.py
src/inverseinterpolable.py
src/__init__.py
src/translation2D.py
src/rigidtransform2d.py
src/waypoint.py
src/interpolatingdict.py
src/adaptivepurepursuitcontroller.py
src/pathsegment.py
src/pathloader.py
src/path.py
pypathfinder/interpolatingvalue.py
pypathfinder/pathreader.py
pypathfinder/circle.py
pypathfinder/rotation2D.py
pypathfinder/interpolable.py
pypathfinder/peekorator.py
pypathfinder/inverseinterpolable.py
pypathfinder/__init__.py
pypathfinder/translation2D.py
pypathfinder/rigidtransform2d.py
pypathfinder/waypoint.py
pypathfinder/interpolatingdict.py
pypathfinder/adaptivepurepursuitcontroller.py
pypathfinder/pathsegment.py
pypathfinder/pathloader.py
pypathfinder/path.py
pypurepursuit-0.0.7.dist-info/METADATA
pypurepursuit-0.0.7.dist-info/WHEEL
pypurepursuit-0.0.7.dist-info/top_level.txt
pypurepursuit-0.0.7.dist-info/metadata.json
pypurepursuit-0.0.7.dist-info/RECORD
pypurepursuit-0.0.7.dist-info/DESCRIPTION.rst
