Metadata-Version: 2.0
Name: pypurepursuit
Version: 0.0.7
Summary: Pure Pursuit controller based on FRC Team 254's code
Home-page: https://github.com/DrWateryCat/pypurepursuit
Author: Kenny Raisbeck
Author-email: UNKNOWN
License: UNKNOWN
Platform: UNKNOWN
Classifier: Programming Language :: Python :: 3.5
